woshi/__init__.py
woshi/constants.py
woshi/woshi.py
woshi-2.1.4.dist-info/WHEEL
woshi-2.1.4.dist-info/METADATA
woshi-2.1.4.dist-info/licenses/LICENSE
woshi-2.1.4.dist-info/RECORD
