Metadata-Version: 2.1
Name: woshi
Version: 2.1.4
Summary: On-the-go HTML Abstraction and Generator for Python
License: LICENSE.txt
Keywords: html,abstraction,template,python
Author: Rodney Maniego Jr.
Author-email: rodney.maniegojr@gmail.com
Requires-Python: >=3.10
Classifier: Development Status :: 5 - Production/Stable
Classifier: Intended Audience :: Developers
Classifier: License :: OSI Approved :: MIT License
Classifier: Programming Language :: Python :: 3
Classifier: Topic :: Software Development :: Build Tools
Project-URL: documentation, https://woshi.readthedocs.io
Project-URL: homepage, https://github.com/rmaniego/woshi
